{
  "STUDENT_URL": "https://go.najottalim.uz",
  "LANDING_URL": "https://najottalim.uz",
  "student_name": "Testing",
  "telegram_nickname": "@najottalim",
  "student_phone": "124574120",
  "student_email": "javohirwebdev@gmail.com",
  "student_pwd": "12345678",

  "TEST_PHONE": "001112233",
  "TEST_EMAIL": "mail@mail.uz",
  "TEST_PWD": "qwerty123",

  "TELEGRAM_TOKEN": "6681396777:AAF6iYwVjMvyq9lyjNBhDZEJwBKHO9odZNo",

  "OTP": "123456",
  "CERTIFICATE_ID_LENGTH": 12,
  "LESSON_NOTE": "SHU JOYIGA TUSHUNMADIMOOOV",
  "SHORT_WAIT": 1000,
  "MID_WAIT": 2000,
  "LONG_WAIT": 3000,

  "COURSE_TITLE": "dasturlash"
}